{
  "customCode" : {
    "responseProcessorName" : "com.events.postprocessors.AgendaProcessor"
  },
  "operationConfig" : {
    "name" : "queryevent_sessions4795",
    "type" : "MappedToBackend",
    "cachable" : false,
    "smsEnabled" : false,
    "security" : "authorized_app_user",
    "responseEncoding" : "UTF-8",
    "httpMethod" : "GET",
    "decodeResponseBody" : false,
    "referencingEndpoint" : "default",
    "odata" : [ {
      "id" : "$select",
      "dataType" : "string",
      "encode" : true,
      "accessType" : "readonly"
    }, {
      "id" : "$filter",
      "dataType" : "string",
      "defaultValue" : "(SoftDeleteFlag ne true) or (SoftDeleteFlag eq null)",
      "encode" : true,
      "accessType" : "readonly"
    }, {
      "id" : "$orderby",
      "dataType" : "string",
      "defaultValue" : "session_start_date",
      "encode" : true,
      "accessType" : "readonly"
    }, {
      "id" : "$top",
      "dataType" : "string",
      "encode" : true,
      "accessType" : "readonly"
    }, {
      "id" : "$skip",
      "dataType" : "string",
      "encode" : true,
      "accessType" : "readonly"
    }, {
      "id" : "$expand",
      "dataType" : "string",
      "defaultValue" : "presenter,session_material",
      "encode" : true,
      "accessType" : "readonly"
    } ],
    "applyCommonMapping" : true,
    "applyRequestCommonMapping" : true,
    "applyResponseCommonMapping" : true,
    "opcode" : "query",
    "relationshipHierarchyMapping" : {
      "children" : [ {
        "actionsAllSelected" : true,
        "children" : [ ],
        "name" : "event_inner_location",
        "actions" : {
          "get" : true
        },
        "actionsPartiallySelected" : false,
        "selected" : true
      }, {
        "actionsAllSelected" : true,
        "children" : [ {
          "actionsAllSelected" : true,
          "children" : [ ],
          "name" : "forum_discussion",
          "actions" : {
            "get" : true
          },
          "actionsPartiallySelected" : false,
          "selected" : true
        } ],
        "name" : "forum",
        "actions" : {
          "get" : true
        },
        "actionsPartiallySelected" : false,
        "selected" : true
      }, {
        "actionsAllSelected" : true,
        "children" : [ ],
        "name" : "location",
        "actions" : {
          "get" : true
        },
        "actionsPartiallySelected" : false,
        "selected" : true
      }, {
        "actionsAllSelected" : true,
        "children" : [ {
          "actionsAllSelected" : true,
          "children" : [ ],
          "name" : "opinion_answers",
          "actions" : {
            "get" : true
          },
          "actionsPartiallySelected" : false,
          "selected" : true
        }, {
          "actionsAllSelected" : true,
          "children" : [ {
            "actionsAllSelected" : true,
            "children" : [ ],
            "name" : "opinion_answers",
            "actions" : {
              "get" : true
            },
            "actionsPartiallySelected" : false,
            "selected" : true
          }, {
            "actionsAllSelected" : true,
            "children" : [ {
              "actionsAllSelected" : true,
              "children" : [ ],
              "name" : "opinion_answers",
              "actions" : {
                "get" : true
              },
              "actionsPartiallySelected" : false,
              "selected" : true
            } ],
            "name" : "opinion_options",
            "actions" : {
              "get" : true
            },
            "actionsPartiallySelected" : false,
            "selected" : true
          } ],
          "name" : "opinion_questions",
          "actions" : {
            "get" : true
          },
          "actionsPartiallySelected" : false,
          "selected" : true
        } ],
        "name" : "opinions",
        "actions" : {
          "get" : true
        },
        "actionsPartiallySelected" : false,
        "selected" : true
      }, {
        "actionsAllSelected" : true,
        "children" : [ ],
        "name" : "participation",
        "actions" : {
          "get" : true
        },
        "actionsPartiallySelected" : false,
        "selected" : true
      }, {
        "actionsAllSelected" : true,
        "children" : [ ],
        "name" : "presenter",
        "actions" : {
          "get" : true
        },
        "actionsPartiallySelected" : false,
        "selected" : true
      }, {
        "actionsAllSelected" : true,
        "children" : [ ],
        "name" : "session_material",
        "actions" : {
          "get" : true
        },
        "actionsPartiallySelected" : false,
        "selected" : true
      }, {
        "actionsAllSelected" : true,
        "children" : [ ],
        "name" : "user_event_session",
        "actions" : {
          "get" : true
        },
        "actionsPartiallySelected" : false,
        "selected" : true
      } ],
      "name" : "event_sessions",
      "actions" : {
        "get" : true
      },
      "selected" : true
    },
    "requestXmlMappingOverride" : false,
    "responseXmlMappingOverride" : false
  }
}