[ {
  "entityTypeId" : "36de97db-326b-4e16-ba34-a088bd2a35d8",
  "id" : "d6a7a9ce-8609-4dcb-8a15-74ca3d2fd209",
  "name" : "CreatedBy",
  "dataType" : "string",
  "hasIndex" : false,
  "unique" : false,
  "primarykey" : false,
  "namefield" : false,
  "nullable" : true,
  "custom" : true,
  "createable" : true,
  "updateable" : true,
  "audit" : false,
  "customizable" : false,
  "fieldLength" : 32,
  "fieldOrder" : 7,
  "fieldProperties" : {
    "standard" : "true",
    "autoGenerated" : "false",
    "isUpdateTimeStampField" : "false",
    "isSoftDeleteField" : "false"
  }
}, {
  "entityTypeId" : "36de97db-326b-4e16-ba34-a088bd2a35d8",
  "id" : "94a98e20-7516-4e1c-bbcf-2fa4727c8fb6",
  "name" : "CreatedDateTime",
  "dataType" : "date",
  "hasIndex" : false,
  "unique" : false,
  "primarykey" : false,
  "namefield" : false,
  "nullable" : false,
  "custom" : true,
  "createable" : false,
  "updateable" : true,
  "audit" : false,
  "customizable" : false,
  "fieldLength" : 32,
  "fieldOrder" : 9,
  "fieldProperties" : {
    "standard" : "true",
    "autoGenerated" : "false",
    "isUpdateTimeStampField" : "false",
    "isSoftDeleteField" : "false"
  }
}, {
  "entityTypeId" : "36de97db-326b-4e16-ba34-a088bd2a35d8",
  "id" : "6ac318bf-9dbb-4fea-a54c-d8a272873421",
  "name" : "LastUpdatedBy",
  "dataType" : "string",
  "hasIndex" : false,
  "unique" : false,
  "primarykey" : false,
  "namefield" : false,
  "nullable" : true,
  "custom" : true,
  "createable" : true,
  "updateable" : true,
  "audit" : false,
  "customizable" : false,
  "fieldLength" : 32,
  "fieldOrder" : 8,
  "fieldProperties" : {
    "standard" : "true",
    "autoGenerated" : "false",
    "isUpdateTimeStampField" : "false",
    "isSoftDeleteField" : "false"
  }
}, {
  "entityTypeId" : "36de97db-326b-4e16-ba34-a088bd2a35d8",
  "id" : "5d8c9203-7a56-4b74-b94a-8a7316b7187c",
  "name" : "LastUpdatedDateTime",
  "dataType" : "date",
  "hasIndex" : false,
  "unique" : false,
  "primarykey" : false,
  "namefield" : false,
  "nullable" : false,
  "custom" : true,
  "createable" : false,
  "updateable" : true,
  "audit" : false,
  "customizable" : false,
  "fieldLength" : 32,
  "fieldOrder" : 10,
  "fieldProperties" : {
    "standard" : "true",
    "autoGenerated" : "false",
    "isUpdateTimeStampField" : "true",
    "isSoftDeleteField" : "false",
    "timeStampFieldFormat" : "yyyy-MM-dd'T'HH:mm:ss.SSS"
  }
}, {
  "entityTypeId" : "36de97db-326b-4e16-ba34-a088bd2a35d8",
  "id" : "37f66f8e-5d48-4272-99a0-7a29685a3bee",
  "name" : "opinion_answer_id",
  "dataType" : "number",
  "hasIndex" : false,
  "unique" : true,
  "primarykey" : true,
  "namefield" : false,
  "nullable" : false,
  "custom" : true,
  "createable" : false,
  "updateable" : true,
  "audit" : false,
  "customizable" : false,
  "fieldOrder" : 1,
  "fieldProperties" : {
    "autoGenerated" : "true"
  }
}, {
  "entityTypeId" : "36de97db-326b-4e16-ba34-a088bd2a35d8",
  "id" : "f66d754a-6b33-4120-b1b2-99ebbde58f16",
  "name" : "opinion_id",
  "dataType" : "number",
  "hasIndex" : false,
  "unique" : false,
  "primarykey" : false,
  "namefield" : false,
  "nullable" : true,
  "custom" : true,
  "createable" : true,
  "updateable" : true,
  "audit" : false,
  "customizable" : false,
  "fieldOrder" : 6,
  "fieldProperties" : {
    "autoGenerated" : "false"
  }
}, {
  "entityTypeId" : "36de97db-326b-4e16-ba34-a088bd2a35d8",
  "id" : "c6017551-b71a-4b42-9c56-357c42dda2e1",
  "name" : "opinion_option_id",
  "dataType" : "number",
  "hasIndex" : false,
  "unique" : false,
  "primarykey" : false,
  "namefield" : false,
  "nullable" : true,
  "custom" : true,
  "createable" : true,
  "updateable" : true,
  "audit" : false,
  "customizable" : false,
  "fieldOrder" : 4,
  "fieldProperties" : {
    "autoGenerated" : "false"
  }
}, {
  "entityTypeId" : "36de97db-326b-4e16-ba34-a088bd2a35d8",
  "id" : "120b7c84-0643-40b6-bfd7-880a7f06c145",
  "name" : "opinion_question_id",
  "dataType" : "number",
  "hasIndex" : false,
  "unique" : false,
  "primarykey" : false,
  "namefield" : false,
  "nullable" : true,
  "custom" : true,
  "createable" : true,
  "updateable" : true,
  "audit" : false,
  "customizable" : false,
  "fieldOrder" : 3,
  "fieldProperties" : {
    "autoGenerated" : "false"
  }
}, {
  "entityTypeId" : "36de97db-326b-4e16-ba34-a088bd2a35d8",
  "id" : "a8bf5a34-f0c7-4a78-8801-9bbdd60cbe94",
  "name" : "response_text",
  "dataType" : "string",
  "hasIndex" : false,
  "unique" : false,
  "primarykey" : false,
  "namefield" : false,
  "nullable" : true,
  "custom" : true,
  "createable" : true,
  "updateable" : true,
  "audit" : false,
  "customizable" : false,
  "fieldLength" : 2000,
  "fieldOrder" : 5,
  "fieldProperties" : {
    "autoGenerated" : "false"
  }
}, {
  "entityTypeId" : "36de97db-326b-4e16-ba34-a088bd2a35d8",
  "id" : "a618738d-6d2a-4ad8-b22a-c1a6a7744b14",
  "name" : "SoftDeleteFlag",
  "dataType" : "boolean",
  "hasIndex" : false,
  "unique" : false,
  "primarykey" : false,
  "namefield" : false,
  "nullable" : true,
  "custom" : true,
  "createable" : false,
  "updateable" : true,
  "audit" : false,
  "customizable" : false,
  "fieldLength" : 1,
  "fieldOrder" : 11,
  "fieldProperties" : {
    "standard" : "true",
    "autoGenerated" : "false",
    "isUpdateTimeStampField" : "false",
    "isSoftDeleteField" : "true"
  }
}, {
  "entityTypeId" : "36de97db-326b-4e16-ba34-a088bd2a35d8",
  "id" : "58e93e83-cf28-4868-8d6b-1ff08fbec206",
  "name" : "user_id",
  "dataType" : "number",
  "hasIndex" : false,
  "unique" : false,
  "primarykey" : false,
  "namefield" : false,
  "nullable" : true,
  "custom" : true,
  "createable" : true,
  "updateable" : true,
  "audit" : false,
  "customizable" : false,
  "fieldOrder" : 2,
  "fieldProperties" : {
    "autoGenerated" : "false"
  }
} ]