{
    "AS_Form_cf489b0ecd8f47ffbea4f99593800e5c": {
        "id": "AS_Form_cf489b0ecd8f47ffbea4f99593800e5c",
        "type": "ACTION_SEQUENCE",
        "params": [{
            "datatype": "collection",
            "name": "eventobject"
        }],
        "contextObj": {
            "name": "frmWifiInfo",
            "type": "forms",
            "platform": "",
            "KUID": "jec7a8f26da3470699013344b9d3e7d7"
        },
        "language": "js",
        "actions": [{
            "id": "ADD_SNIPPET__jfa342d2a4a241c993cbcf7db229cabc",
            "type": "ADD_SNIPPET",
            "codeSnippet": "this.formWifiInfoPostShowAction();",
            "parentId": null,
            "callbackType": null
        }]
    }
}